[
    {
        "gender": "Male",
        "age": 56,
        "name": "Daniel Castillo",
        "address": {
            "city": "Mexico City",
            "street": "Bicentenario",
            "neighborhood": "Condesa",
            "number": 158,
            "zipcode": 64331
        }
    },
    {
        "gender": "Not defined",
        "age": 23,
        "name": "Daniel Diaz",
        "address": {
            "city": "Mexico City",
            "street": "Juarez",
            "neighborhood": "Narvarte",
            "number": 93,
            "zipcode": 57540
        }
    },
    {
        "gender": "Not defined",
        "age": 58,
        "name": "Carlos Escamilla",
        "address": {
            "city": "Mexico City",
            "street": "Rojo Gomez",
            "neighborhood": "Condesa",
            "number": 12,
            "zipcode": 53908
        }
    },
    {
        "gender": "Female",
        "age": 58,
        "name": "Gerardo Fernandez",
        "address": {
            "city": "Mexico City",
            "street": "Reforma",
            "neighborhood": "Roma Norte",
            "number": 81,
            "zipcode": 66758
        }
    },
    {
        "gender": "Male",
        "age": 71,
        "name": "Daniel Escamilla",
        "address": {
            "city": "Mexico City",
            "street": "Bicentenario",
            "neighborhood": "Condesa",
            "number": 12,
            "zipcode": 99867
        }
    },
    {
        "gender": "Male",
        "age": 17,
        "name": "Gerardo Alvarez",
        "address": {
            "city": "Mexico City",
            "street": "Rojo Gomez",
            "neighborhood": "Roma Norte",
            "number": 27,
            "zipcode": 22867
        }
    },
    {
        "gender": "Not defined",
        "age": 28,
        "name": "Gerardo Castillo",
        "address": {
            "city": "Mexico City",
            "street": "Juarez",
            "neighborhood": "Condesa",
            "number": 42,
            "zipcode": 66037
        }
    },
    {
        "gender": "Male",
        "age": 23,
        "name": "Ana Diaz",
        "address": {
            "city": "Mexico City",
            "street": "Juarez",
            "neighborhood": "Roma Norte",
            "number": 205,
            "zipcode": 89510
        }
    },
    {
        "gender": "Male",
        "age": 14,
        "name": "Carlos Castillo",
        "address": {
            "city": "Mexico City",
            "street": "Juarez",
            "neighborhood": "Narvarte",
            "number": 20,
            "zipcode": 37992
        }
    },
    {
        "gender": "Female",
        "age": 79,
        "name": "Gerardo Alvarez",
        "address": {
            "city": "Mexico City",
            "street": "Juarez",
            "neighborhood": "Condesa",
            "number": 345,
            "zipcode": 16247
        }
    },
    {
        "gender": "Not defined",
        "age": 21,
        "name": "Ana Fernandez",
        "address": {
            "city": "Mexico City",
            "street": "Juarez",
            "neighborhood": "Narvarte",
            "number": 400,
            "zipcode": 11865
        }
    },
    {
        "gender": "Female",
        "age": 73,
        "name": "Edna Alvarez",
        "address": {
            "city": "Mexico City",
            "street": "Reforma",
            "neighborhood": "Condesa",
            "number": 347,
            "zipcode": 76234
        }
    },
    {
        "gender": "Not defined",
        "age": 80,
        "name": "Beto Castillo",
        "address": {
            "city": "Mexico City",
            "street": "Bicentenario",
            "neighborhood": "Narvarte",
            "number": 49,
            "zipcode": 30243
        }
    },
    {
        "gender": "Female",
        "age": 10,
        "name": "Daniel Fernandez",
        "address": {
            "city": "Mexico City",
            "street": "Rojo Gomez",
            "neighborhood": "Condesa",
            "number": 225,
            "zipcode": 41538
        }
    },
    {
        "gender": "Not defined",
        "age": 37,
        "name": "Fatima Alvarez",
        "address": {
            "city": "Mexico City",
            "street": "Juarez",
            "neighborhood": "Roma Norte",
            "number": 274,
            "zipcode": 38608
        }
    },
    {
        "gender": "Male",
        "age": 68,
        "name": "Fatima Alvarez",
        "address": {
            "city": "Mexico City",
            "street": "Rojo Gomez",
            "neighborhood": "Roma Norte",
            "number": 117,
            "zipcode": 34031
        }
    },
    {
        "gender": "Not defined",
        "age": 26,
        "name": "Daniel Diaz",
        "address": {
            "city": "Mexico City",
            "street": "Rojo Gomez",
            "neighborhood": "Narvarte",
            "number": 13,
            "zipcode": 18768
        }
    },
    {
        "gender": "Not defined",
        "age": 25,
        "name": "Daniel Benitez",
        "address": {
            "city": "Mexico City",
            "street": "Rojo Gomez",
            "neighborhood": "Roma Norte",
            "number": 221,
            "zipcode": 74699
        }
    },
    {
        "gender": "Male",
        "age": 12,
        "name": "Edna Alvarez",
        "address": {
            "city": "Mexico City",
            "street": "Juarez",
            "neighborhood": "Condesa",
            "number": 375,
            "zipcode": 67310
        }
    },
    {
        "gender": "Male",
        "age": 12,
        "name": "Fatima Benitez",
        "address": {
            "city": "Mexico City",
            "street": "Reforma",
            "neighborhood": "Condesa",
            "number": 57,
            "zipcode": 98684
        }
    },
    {
        "gender": "Male",
        "age": 76,
        "name": "Ana Escamilla",
        "address": {
            "city": "Mexico City",
            "street": "Rojo Gomez",
            "neighborhood": "Narvarte",
            "number": 161,
            "zipcode": 79106
        }
    },
    {
        "gender": "Female",
        "age": 80,
        "name": "Beto Fernandez",
        "address": {
            "city": "Mexico City",
            "street": "Bicentenario",
            "neighborhood": "Condesa",
            "number": 16,
            "zipcode": 24455
        }
    },
    {
        "gender": "Female",
        "age": 40,
        "name": "Edna Alvarez",
        "address": {
            "city": "Mexico City",
            "street": "Reforma",
            "neighborhood": "Roma Norte",
            "number": 10,
            "zipcode": 22102
        }
    },
    {
        "gender": "Male",
        "age": 19,
        "name": "Daniel Diaz",
        "address": {
            "city": "Mexico City",
            "street": "Bicentenario",
            "neighborhood": "Condesa",
            "number": 40,
            "zipcode": 97554
        }
    },
    {
        "gender": "Male",
        "age": 69,
        "name": "Gerardo Fernandez",
        "address": {
            "city": "Mexico City",
            "street": "Juarez",
            "neighborhood": "Condesa",
            "number": 87,
            "zipcode": 51286
        }
    },
    {
        "gender": "Female",
        "age": 26,
        "name": "Edna Alvarez",
        "address": {
            "city": "Mexico City",
            "street": "Bicentenario",
            "neighborhood": "Roma Norte",
            "number": 192,
            "zipcode": 39911
        }
    },
    {
        "gender": "Female",
        "age": 1,
        "name": "Daniel Fernandez",
        "address": {
            "city": "Mexico City",
            "street": "Juarez",
            "neighborhood": "Condesa",
            "number": 318,
            "zipcode": 63843
        }
    },
    {
        "gender": "Male",
        "age": 38,
        "name": "Daniel Benitez",
        "address": {
            "city": "Mexico City",
            "street": "Bicentenario",
            "neighborhood": "Narvarte",
            "number": 98,
            "zipcode": 89155
        }
    },
    {
        "gender": "Male",
        "age": 30,
        "name": "Gerardo Benitez",
        "address": {
            "city": "Mexico City",
            "street": "Bicentenario",
            "neighborhood": "Narvarte",
            "number": 237,
            "zipcode": 53901
        }
    },
    {
        "gender": "Not defined",
        "age": 17,
        "name": "Daniel Castillo",
        "address": {
            "city": "Mexico City",
            "street": "Reforma",
            "neighborhood": "Roma Norte",
            "number": 271,
            "zipcode": 42631
        }
    },
    {
        "gender": "Not defined",
        "age": 74,
        "name": "Gerardo Alvarez",
        "address": {
            "city": "Mexico City",
            "street": "Rojo Gomez",
            "neighborhood": "Narvarte",
            "number": 295,
            "zipcode": 59634
        }
    },
    {
        "gender": "Female",
        "age": 4,
        "name": "Beto Fernandez",
        "address": {
            "city": "Mexico City",
            "street": "Reforma",
            "neighborhood": "Roma Norte",
            "number": 389,
            "zipcode": 96592
        }
    },
    {
        "gender": "Not defined",
        "age": 63,
        "name": "Fatima Alvarez",
        "address": {
            "city": "Mexico City",
            "street": "Bicentenario",
            "neighborhood": "Condesa",
            "number": 318,
            "zipcode": 99744
        }
    },
    {
        "gender": "Female",
        "age": 0,
        "name": "Edna Escamilla",
        "address": {
            "city": "Mexico City",
            "street": "Juarez",
            "neighborhood": "Condesa",
            "number": 74,
            "zipcode": 35838
        }
    },
    {
        "gender": "Not defined",
        "age": 17,
        "name": "Ana Diaz",
        "address": {
            "city": "Mexico City",
            "street": "Bicentenario",
            "neighborhood": "Roma Norte",
            "number": 284,
            "zipcode": 80581
        }
    },
    {
        "gender": "Male",
        "age": 63,
        "name": "Ana Benitez",
        "address": {
            "city": "Mexico City",
            "street": "Rojo Gomez",
            "neighborhood": "Narvarte",
            "number": 342,
            "zipcode": 40342
        }
    },
    {
        "gender": "Male",
        "age": 27,
        "name": "Ana Benitez",
        "address": {
            "city": "Mexico City",
            "street": "Bicentenario",
            "neighborhood": "Condesa",
            "number": 257,
            "zipcode": 50479
        }
    },
    {
        "gender": "Male",
        "age": 48,
        "name": "Fatima Castillo",
        "address": {
            "city": "Mexico City",
            "street": "Reforma",
            "neighborhood": "Condesa",
            "number": 339,
            "zipcode": 52794
        }
    },
    {
        "gender": "Not defined",
        "age": 19,
        "name": "Daniel Castillo",
        "address": {
            "city": "Mexico City",
            "street": "Juarez",
            "neighborhood": "Roma Norte",
            "number": 163,
            "zipcode": 37800
        }
    },
    {
        "gender": "Not defined",
        "age": 55,
        "name": "Fatima Alvarez",
        "address": {
            "city": "Mexico City",
            "street": "Bicentenario",
            "neighborhood": "Roma Norte",
            "number": 106,
            "zipcode": 40399
        }
    },
    {
        "gender": "Female",
        "age": 51,
        "name": "Beto Castillo",
        "address": {
            "city": "Mexico City",
            "street": "Juarez",
            "neighborhood": "Narvarte",
            "number": 238,
            "zipcode": 96281
        }
    },
    {
        "gender": "Female",
        "age": 71,
        "name": "Daniel Alvarez",
        "address": {
            "city": "Mexico City",
            "street": "Juarez",
            "neighborhood": "Narvarte",
            "number": 353,
            "zipcode": 87151
        }
    },
    {
        "gender": "Not defined",
        "age": 33,
        "name": "Carlos Escamilla",
        "address": {
            "city": "Mexico City",
            "street": "Rojo Gomez",
            "neighborhood": "Roma Norte",
            "number": 288,
            "zipcode": 60490
        }
    },
    {
        "gender": "Female",
        "age": 79,
        "name": "Daniel Alvarez",
        "address": {
            "city": "Mexico City",
            "street": "Rojo Gomez",
            "neighborhood": "Narvarte",
            "number": 244,
            "zipcode": 94284
        }
    },
    {
        "gender": "Not defined",
        "age": 58,
        "name": "Edna Castillo",
        "address": {
            "city": "Mexico City",
            "street": "Rojo Gomez",
            "neighborhood": "Roma Norte",
            "number": 244,
            "zipcode": 44958
        }
    },
    {
        "gender": "Male",
        "age": 74,
        "name": "Daniel Alvarez",
        "address": {
            "city": "Mexico City",
            "street": "Juarez",
            "neighborhood": "Condesa",
            "number": 29,
            "zipcode": 60584
        }
    },
    {
        "gender": "Female",
        "age": 63,
        "name": "Gerardo Benitez",
        "address": {
            "city": "Mexico City",
            "street": "Juarez",
            "neighborhood": "Roma Norte",
            "number": 204,
            "zipcode": 32454
        }
    },
    {
        "gender": "Not defined",
        "age": 19,
        "name": "Edna Castillo",
        "address": {
            "city": "Mexico City",
            "street": "Juarez",
            "neighborhood": "Roma Norte",
            "number": 340,
            "zipcode": 42172
        }
    },
    {
        "gender": "Male",
        "age": 75,
        "name": "Daniel Alvarez",
        "address": {
            "city": "Mexico City",
            "street": "Rojo Gomez",
            "neighborhood": "Narvarte",
            "number": 317,
            "zipcode": 41629
        }
    },
    {
        "gender": "Not defined",
        "age": 71,
        "name": "Gerardo Alvarez",
        "address": {
            "city": "Mexico City",
            "street": "Bicentenario",
            "neighborhood": "Condesa",
            "number": 355,
            "zipcode": 58445
        }
    },
    {
        "gender": "Not defined",
        "age": 12,
        "name": "Carlos Escamilla",
        "address": {
            "city": "Mexico City",
            "street": "Juarez",
            "neighborhood": "Roma Norte",
            "number": 352,
            "zipcode": 57502
        }
    },
    {
        "gender": "Male",
        "age": 17,
        "name": "Fatima Escamilla",
        "address": {
            "city": "Mexico City",
            "street": "Bicentenario",
            "neighborhood": "Condesa",
            "number": 280,
            "zipcode": 93656
        }
    },
    {
        "gender": "Female",
        "age": 1,
        "name": "Ana Escamilla",
        "address": {
            "city": "Mexico City",
            "street": "Juarez",
            "neighborhood": "Condesa",
            "number": 237,
            "zipcode": 45909
        }
    },
    {
        "gender": "Male",
        "age": 1,
        "name": "Beto Alvarez",
        "address": {
            "city": "Mexico City",
            "street": "Reforma",
            "neighborhood": "Narvarte",
            "number": 2,
            "zipcode": 12166
        }
    },
    {
        "gender": "Male",
        "age": 22,
        "name": "Edna Escamilla",
        "address": {
            "city": "Mexico City",
            "street": "Reforma",
            "neighborhood": "Roma Norte",
            "number": 130,
            "zipcode": 13977
        }
    },
    {
        "gender": "Male",
        "age": 59,
        "name": "Gerardo Diaz",
        "address": {
            "city": "Mexico City",
            "street": "Juarez",
            "neighborhood": "Narvarte",
            "number": 375,
            "zipcode": 12228
        }
    },
    {
        "gender": "Female",
        "age": 18,
        "name": "Daniel Alvarez",
        "address": {
            "city": "Mexico City",
            "street": "Bicentenario",
            "neighborhood": "Narvarte",
            "number": 160,
            "zipcode": 72700
        }
    },
    {
        "gender": "Female",
        "age": 43,
        "name": "Fatima Diaz",
        "address": {
            "city": "Mexico City",
            "street": "Juarez",
            "neighborhood": "Condesa",
            "number": 358,
            "zipcode": 83674
        }
    },
    {
        "gender": "Male",
        "age": 55,
        "name": "Edna Diaz",
        "address": {
            "city": "Mexico City",
            "street": "Juarez",
            "neighborhood": "Roma Norte",
            "number": 184,
            "zipcode": 72548
        }
    },
    {
        "gender": "Female",
        "age": 70,
        "name": "Gerardo Castillo",
        "address": {
            "city": "Mexico City",
            "street": "Rojo Gomez",
            "neighborhood": "Narvarte",
            "number": 12,
            "zipcode": 27491
        }
    },
    {
        "gender": "Male",
        "age": 9,
        "name": "Beto Benitez",
        "address": {
            "city": "Mexico City",
            "street": "Juarez",
            "neighborhood": "Roma Norte",
            "number": 236,
            "zipcode": 57106
        }
    },
    {
        "gender": "Female",
        "age": 31,
        "name": "Ana Benitez",
        "address": {
            "city": "Mexico City",
            "street": "Bicentenario",
            "neighborhood": "Condesa",
            "number": 77,
            "zipcode": 81499
        }
    },
    {
        "gender": "Male",
        "age": 4,
        "name": "Ana Benitez",
        "address": {
            "city": "Mexico City",
            "street": "Juarez",
            "neighborhood": "Roma Norte",
            "number": 246,
            "zipcode": 44793
        }
    },
    {
        "gender": "Male",
        "age": 71,
        "name": "Beto Diaz",
        "address": {
            "city": "Mexico City",
            "street": "Rojo Gomez",
            "neighborhood": "Narvarte",
            "number": 220,
            "zipcode": 86569
        }
    },
    {
        "gender": "Not defined",
        "age": 66,
        "name": "Edna Alvarez",
        "address": {
            "city": "Mexico City",
            "street": "Juarez",
            "neighborhood": "Roma Norte",
            "number": 124,
            "zipcode": 54077
        }
    },
    {
        "gender": "Not defined",
        "age": 53,
        "name": "Daniel Fernandez",
        "address": {
            "city": "Mexico City",
            "street": "Rojo Gomez",
            "neighborhood": "Roma Norte",
            "number": 181,
            "zipcode": 91071
        }
    },
    {
        "gender": "Not defined",
        "age": 56,
        "name": "Fatima Escamilla",
        "address": {
            "city": "Mexico City",
            "street": "Bicentenario",
            "neighborhood": "Narvarte",
            "number": 219,
            "zipcode": 97839
        }
    },
    {
        "gender": "Female",
        "age": 80,
        "name": "Ana Castillo",
        "address": {
            "city": "Mexico City",
            "street": "Rojo Gomez",
            "neighborhood": "Condesa",
            "number": 181,
            "zipcode": 63862
        }
    },
    {
        "gender": "Not defined",
        "age": 43,
        "name": "Daniel Benitez",
        "address": {
            "city": "Mexico City",
            "street": "Rojo Gomez",
            "neighborhood": "Roma Norte",
            "number": 296,
            "zipcode": 74146
        }
    },
    {
        "gender": "Not defined",
        "age": 16,
        "name": "Edna Escamilla",
        "address": {
            "city": "Mexico City",
            "street": "Rojo Gomez",
            "neighborhood": "Roma Norte",
            "number": 333,
            "zipcode": 16779
        }
    },
    {
        "gender": "Female",
        "age": 47,
        "name": "Beto Escamilla",
        "address": {
            "city": "Mexico City",
            "street": "Bicentenario",
            "neighborhood": "Narvarte",
            "number": 290,
            "zipcode": 96435
        }
    },
    {
        "gender": "Not defined",
        "age": 37,
        "name": "Fatima Diaz",
        "address": {
            "city": "Mexico City",
            "street": "Juarez",
            "neighborhood": "Narvarte",
            "number": 387,
            "zipcode": 15263
        }
    },
    {
        "gender": "Not defined",
        "age": 56,
        "name": "Edna Castillo",
        "address": {
            "city": "Mexico City",
            "street": "Juarez",
            "neighborhood": "Condesa",
            "number": 258,
            "zipcode": 46647
        }
    },
    {
        "gender": "Not defined",
        "age": 76,
        "name": "Beto Escamilla",
        "address": {
            "city": "Mexico City",
            "street": "Reforma",
            "neighborhood": "Narvarte",
            "number": 123,
            "zipcode": 70017
        }
    },
    {
        "gender": "Not defined",
        "age": 71,
        "name": "Gerardo Castillo",
        "address": {
            "city": "Mexico City",
            "street": "Bicentenario",
            "neighborhood": "Condesa",
            "number": 30,
            "zipcode": 64400
        }
    },
    {
        "gender": "Male",
        "age": 20,
        "name": "Carlos Alvarez",
        "address": {
            "city": "Mexico City",
            "street": "Rojo Gomez",
            "neighborhood": "Roma Norte",
            "number": 46,
            "zipcode": 67699
        }
    },
    {
        "gender": "Male",
        "age": 37,
        "name": "Ana Diaz",
        "address": {
            "city": "Mexico City",
            "street": "Juarez",
            "neighborhood": "Condesa",
            "number": 122,
            "zipcode": 71738
        }
    },
    {
        "gender": "Male",
        "age": 26,
        "name": "Gerardo Benitez",
        "address": {
            "city": "Mexico City",
            "street": "Juarez",
            "neighborhood": "Roma Norte",
            "number": 43,
            "zipcode": 46111
        }
    },
    {
        "gender": "Female",
        "age": 68,
        "name": "Ana Diaz",
        "address": {
            "city": "Mexico City",
            "street": "Reforma",
            "neighborhood": "Condesa",
            "number": 42,
            "zipcode": 93382
        }
    },
    {
        "gender": "Female",
        "age": 72,
        "name": "Fatima Benitez",
        "address": {
            "city": "Mexico City",
            "street": "Juarez",
            "neighborhood": "Roma Norte",
            "number": 386,
            "zipcode": 46205
        }
    },
    {
        "gender": "Male",
        "age": 11,
        "name": "Ana Alvarez",
        "address": {
            "city": "Mexico City",
            "street": "Rojo Gomez",
            "neighborhood": "Condesa",
            "number": 46,
            "zipcode": 37509
        }
    },
    {
        "gender": "Male",
        "age": 63,
        "name": "Daniel Alvarez",
        "address": {
            "city": "Mexico City",
            "street": "Reforma",
            "neighborhood": "Condesa",
            "number": 361,
            "zipcode": 79375
        }
    },
    {
        "gender": "Not defined",
        "age": 80,
        "name": "Fatima Escamilla",
        "address": {
            "city": "Mexico City",
            "street": "Juarez",
            "neighborhood": "Roma Norte",
            "number": 148,
            "zipcode": 38046
        }
    },
    {
        "gender": "Not defined",
        "age": 53,
        "name": "Carlos Benitez",
        "address": {
            "city": "Mexico City",
            "street": "Bicentenario",
            "neighborhood": "Narvarte",
            "number": 304,
            "zipcode": 52062
        }
    },
    {
        "gender": "Male",
        "age": 59,
        "name": "Fatima Diaz",
        "address": {
            "city": "Mexico City",
            "street": "Reforma",
            "neighborhood": "Condesa",
            "number": 394,
            "zipcode": 80121
        }
    },
    {
        "gender": "Male",
        "age": 44,
        "name": "Ana Alvarez",
        "address": {
            "city": "Mexico City",
            "street": "Bicentenario",
            "neighborhood": "Roma Norte",
            "number": 40,
            "zipcode": 13705
        }
    },
    {
        "gender": "Not defined",
        "age": 1,
        "name": "Carlos Diaz",
        "address": {
            "city": "Mexico City",
            "street": "Rojo Gomez",
            "neighborhood": "Condesa",
            "number": 133,
            "zipcode": 16799
        }
    },
    {
        "gender": "Not defined",
        "age": 56,
        "name": "Ana Castillo",
        "address": {
            "city": "Mexico City",
            "street": "Bicentenario",
            "neighborhood": "Condesa",
            "number": 259,
            "zipcode": 51917
        }
    },
    {
        "gender": "Not defined",
        "age": 2,
        "name": "Daniel Diaz",
        "address": {
            "city": "Mexico City",
            "street": "Juarez",
            "neighborhood": "Condesa",
            "number": 375,
            "zipcode": 23801
        }
    },
    {
        "gender": "Female",
        "age": 22,
        "name": "Daniel Fernandez",
        "address": {
            "city": "Mexico City",
            "street": "Rojo Gomez",
            "neighborhood": "Roma Norte",
            "number": 142,
            "zipcode": 45521
        }
    },
    {
        "gender": "Female",
        "age": 59,
        "name": "Gerardo Benitez",
        "address": {
            "city": "Mexico City",
            "street": "Bicentenario",
            "neighborhood": "Narvarte",
            "number": 138,
            "zipcode": 51221
        }
    },
    {
        "gender": "Male",
        "age": 1,
        "name": "Carlos Fernandez",
        "address": {
            "city": "Mexico City",
            "street": "Bicentenario",
            "neighborhood": "Narvarte",
            "number": 217,
            "zipcode": 31498
        }
    },
    {
        "gender": "Male",
        "age": 69,
        "name": "Beto Escamilla",
        "address": {
            "city": "Mexico City",
            "street": "Bicentenario",
            "neighborhood": "Narvarte",
            "number": 168,
            "zipcode": 84165
        }
    },
    {
        "gender": "Not defined",
        "age": 66,
        "name": "Edna Fernandez",
        "address": {
            "city": "Mexico City",
            "street": "Reforma",
            "neighborhood": "Roma Norte",
            "number": 374,
            "zipcode": 55270
        }
    },
    {
        "gender": "Not defined",
        "age": 11,
        "name": "Daniel Fernandez",
        "address": {
            "city": "Mexico City",
            "street": "Juarez",
            "neighborhood": "Roma Norte",
            "number": 33,
            "zipcode": 93839
        }
    },
    {
        "gender": "Female",
        "age": 38,
        "name": "Gerardo Fernandez",
        "address": {
            "city": "Mexico City",
            "street": "Reforma",
            "neighborhood": "Roma Norte",
            "number": 60,
            "zipcode": 81939
        }
    },
    {
        "gender": "Not defined",
        "age": 14,
        "name": "Fatima Fernandez",
        "address": {
            "city": "Mexico City",
            "street": "Bicentenario",
            "neighborhood": "Narvarte",
            "number": 249,
            "zipcode": 64900
        }
    },
    {
        "gender": "Not defined",
        "age": 31,
        "name": "Gerardo Castillo",
        "address": {
            "city": "Mexico City",
            "street": "Rojo Gomez",
            "neighborhood": "Narvarte",
            "number": 321,
            "zipcode": 79427
        }
    },
    {
        "gender": "Not defined",
        "age": 17,
        "name": "Ana Benitez",
        "address": {
            "city": "Mexico City",
            "street": "Bicentenario",
            "neighborhood": "Condesa",
            "number": 69,
            "zipcode": 15724
        }
    },
    {
        "gender": "Male",
        "age": 8,
        "name": "Fatima Escamilla",
        "address": {
            "city": "Mexico City",
            "street": "Rojo Gomez",
            "neighborhood": "Narvarte",
            "number": 45,
            "zipcode": 37826
        }
    }
]